alteryx_gallery_py/__init__.py
alteryx_gallery_py/__main__.py
alteryx_gallery_py/subscriptions.py
alteryx_gallery_py-1.0.1.dist-info/METADATA
alteryx_gallery_py-1.0.1.dist-info/WHEEL
alteryx_gallery_py-1.0.1.dist-info/entry_points.txt
alteryx_gallery_py-1.0.1.dist-info/top_level.txt
alteryx_gallery_py-1.0.1.dist-info/RECORD
