Metadata-Version: 2.1
Name: alteryx-gallery-py
Version: 1.0.1
Summary: Connect to Alteryx Gallery using API
Home-page: https://github.com/continuus-technoloiges/alteryx_gallery_py
Author: Continuus Technologies
Author-email: info@continuus-technologies.com
License: MIT
Platform: UNKNOWN
Classifier: License :: OSI Approved :: MIT License
Classifier: Programming Language :: Python :: 3
Classifier: Programming Language :: Python :: 3.9
